Metadata-Version: 2.1
Name: kirill-tools
Version: 0.0.1
Summary: kirill_tools
Author: Kirill
Author-email: your@domain.com
